LICENSE
MANIFEST.in
README.rst
pyproject.toml
setup.cfg
setup.py
django_email_subscription_app.egg-info/PKG-INFO
django_email_subscription_app.egg-info/SOURCES.txt
django_email_subscription_app.egg-info/dependency_links.txt
django_email_subscription_app.egg-info/requires.txt
django_email_subscription_app.egg-info/top_level.txt
email_app/__init__.py
email_app/admin.py
email_app/apps.py
email_app/email_controller.py
email_app/forms.py
email_app/models.py
email_app/tests.py
email_app/urls.py
email_app/views.py
email_app/migrations/__init__.py
email_app/templates/subscribe_form.html